[
    {
        "id":"98876501", 
        "name":"Salada Ravanello",
        "description":"Rabanetes, folhas verdes e molho agridoce salpicados com gergelim.",
        "price":"49.97",
        "image":"/static/images/Salada-ravanello2.png"
    },

    {
        "id":"98876502", 
        "name":"Torradas de Parma",
        "description":"Presunto de parma e rúcula em um pão com fermentação natural.",
        "price":"25.97",
        "image":"/static/images/Torradas-de-parma2.png"
    },

    {
        "id":"98876503", 
        "name":"Spaguetti Gambe",
        "description":"Massa fresca com camarões e pesto.",
        "price":"79.97",
        "image":"/static/images/Spaguetti-gambe2.png"
    },

    {
        "id":"98876504", 
        "name":"Salada Molla",
        "description":"Tomates, coentro, pepino, cebola roxa. Frescos e temperados.",
        "price":"19.97",
        "image":"/static/images/Salada-molla2.png"
    }
]    

